{
    "metadataAttributes": {
        "Id": "1138",
        "Title": "Inteligencia artificial: proyecto final",
        "URL": "https://www.coursera.org/learn/inteligencia-artificial?specialization=inteligencia-artificial",
        "Short Intro": "En el proyecto culminante del programa especializado Introducci\u00f3n a la Inteligencia Artificial, los estudiantes aplicar\u00e1n conceptos adquiridos durante el programa en un problema de su elecci\u00f3n.",
        "Category": "Computer Science",
        "Sub-Category": "Algorithms",
        "Course Type": "Course",
        "Language": "Spanish",
        "Skills": "",
        "Instructors": "Carlos Gershenson",
        "Rating": "0.0",
        "Number of viewers": "",
        "Duration": "Approx. 24 hours to complete",
        "Site": "Coursera"
    }
}