{
    "metadataAttributes": {
        "Id": "1839",
        "Title": "Enterprise Database Migration",
        "URL": "https://www.coursera.org/learn/enterprise-database-migration?specialization=google-cloud-database-engineer",
        "Short Intro": "This course is intended to give architects, engineers, and developers the skills required to help enterprise customers architect, plan, execute, and test database migration projects. Through a combination of presentations, demos, and hands-on labs participants move databases to Google Cloud while taking advantage of various services. ",
        "Category": "Information Technology",
        "Sub-Category": "Cloud Computing",
        "Course Type": "Course",
        "Language": "English",
        "Skills": "",
        "Instructors": "Google Cloud Training",
        "Rating": "4.6",
        "Number of viewers": "16 ",
        "Duration": "Approx. 19 hours to complete",
        "Site": "Coursera"
    }
}