{
    "metadataAttributes": {
        "Id": "1977",
        "Title": "Copyright Law in the Music Business",
        "URL": "https://www.coursera.org/learn/copyright-law-music-business?specialization=business-music-production",
        "Short Intro": "In this course taught by E. Michael Harrington, students will learn the basis for copyright including what is and is not covered by copyright law. This course will help clarify what rights artists have as creators as well as what the public is free to take from their work. Students will also learn what to do if someone copies their work and what to do if they are accused of copying someone else. Finally, the course will discuss how technology has changed copyright for the better (and worse) and how copyright laws may change in the coming years.",
        "Category": "Business",
        "Sub-Category": "Business Strategy",
        "Course Type": "Course",
        "Language": "English",
        "Skills": "Create music legally,Read Legal Documents,Leverage the copyright law to your advantage,Write a co-writing agreement,",
        "Instructors": "Dr. E. Michael Harrington",
        "Rating": "4.8",
        "Number of viewers": "613 ",
        "Duration": "Approx. 10 hours to complete",
        "Site": "Coursera"
    }
}