{
    "metadataAttributes": {
        "Id": "245",
        "Title": "Python, Bash and SQL Essentials for Data Engineering Specialization",
        "URL": "https://www.coursera.org/specializations/python-bash-sql-data-engineering-duke",
        "Short Intro": "Launch Your Career in Data Engineering. Master foundational strategies and tools to become proficient in developing data engineering and machine learning solutions",
        "Category": "Information Technology",
        "Sub-Category": "Data Management",
        "Course Type": "Specialization",
        "Language": "English",
        "Skills": "Bash (Unix Shell), Database (DBMS), Web Application, Python Programming, SQL, Vim, Pandas, Visual Studio Code, Data Structure, Data Management, Linux, Web Scraping, ",
        "Instructors": "Kennedy Behrman ,Alfredo Deza ,Noah Gift ,",
        "Rating": "4.4",
        "Number of viewers": "172 ",
        "Duration": "Approximately 4 months to complete",
        "Site": "Coursera"
    }
}