{
    "metadataAttributes": {
        "Id": "2456",
        "Title": "Medical Terminology I",
        "URL": "https://www.coursera.org/learn/medical-terminology-1?specialization=medicalterminology",
        "Short Intro": "This course will discuss the importance of learning medical language as well as introduce basic word parts and concepts applied in medical terminology. We will also learn about common organization and terms seen in medical records before moving into system-specific terms for the integumentary system (skin), musculoskeletal system (muscles and bones), and urinary (kidneys).",
        "Category": "Health",
        "Sub-Category": "Basic Science",
        "Course Type": "Course",
        "Language": "English",
        "Skills": "",
        "Instructors": "Laura S. Kabiri",
        "Rating": "4.9",
        "Number of viewers": "216 ",
        "Duration": "Approx. 14 hours to complete",
        "Site": "Coursera"
    }
}