{
    "metadataAttributes": {
        "Id": "2769",
        "Title": "Operations Systems Excellence",
        "URL": "https://www.coursera.org/learn/operations-systems-excellence?specialization=uol-business-and-marketing-strategies",
        "Short Intro": "The sole task of organisations is to either deliver customers the services that they require, or design, manufacture, and deliver products that customers are after. How do firms and organisations manage the very tasks that they carry out? How can operations themselves give excellence to organisations to enable them to be competitive?  ",
        "Category": "Business",
        "Sub-Category": "Business Essentials",
        "Course Type": "Course",
        "Language": "English",
        "Skills": "",
        "Instructors": "Alan Pilkington",
        "Rating": "4.4",
        "Number of viewers": "11 ",
        "Duration": "Approx. 18 hours to complete",
        "Site": "Coursera"
    }
}