{
    "metadataAttributes": {
        "Id": "2953",
        "Title": "App Monetization",
        "URL": "https://www.udacity.com/course/app-monetization--ud518",
        "Short Intro": "Develop a Sustainable Financial Strategy",
        "Category": "",
        "Sub-Category": "",
        "Course Type": "",
        "Language": "",
        "Skills": "",
        "Instructors": "",
        "Rating": "0.0",
        "Number of viewers": "",
        "Duration": "Estimated timeApprox. 1 Month",
        "Site": "Udacity"
    }
}