{
    "metadataAttributes": {
        "Id": "3015",
        "Title": "Front End Web Developer",
        "URL": "https://www.udacity.com/course/front-end-web-developer-nanodegree--nd0011",
        "Short Intro": "Learn how to build high quality websites and dynamic applications to create stunning user experiences for the web.",
        "Category": "",
        "Sub-Category": "",
        "Course Type": "",
        "Language": "",
        "Skills": " Webpack, CSS, Website Performance Optimization, Flexbox, The Document Object Model, SASS, Express Web Framework, DOM Manipulation, DOM Events, Asynchronous JavaScript, HTML, Fetching Data, Application Routing, Code Debugging, JavaScript Package Management, JavaScript Data Structures, Responsive Web Design",
        "Instructors": "",
        "Rating": "4.6",
        "Number of viewers": "",
        "Duration": "4 months to complete",
        "Site": "Udacity"
    }
}