{
    "metadataAttributes": {
        "Id": "3143",
        "Title": "Business Ethics: Exploring Big Data and Tax Avoidance",
        "URL": "https://www.futurelearn.com/courses/business-ethics",
        "Short Intro": "Learn why big data and tax avoidance are some of the biggest ethical issues facing businesses today and how they can be addressed.",
        "Category": "",
        "Sub-Category": "",
        "Course Type": "",
        "Language": "",
        "Skills": "",
        "Instructors": "",
        "Rating": "0.0",
        "Number of viewers": "",
        "Duration": "2 weeks",
        "Site": "Future Learn"
    }
}