{
    "metadataAttributes": {
        "Id": "3173",
        "Title": "Ethical Management and Decision Making",
        "URL": "https://www.futurelearn.com/courses/managing-in-an-ethical-manner",
        "Short Intro": "Get to grips with how to manage ethically with this MOOC developed by the University of Law Business School.",
        "Category": "",
        "Sub-Category": "",
        "Course Type": "",
        "Language": "",
        "Skills": "",
        "Instructors": "",
        "Rating": "0.0",
        "Number of viewers": "",
        "Duration": "3 weeks",
        "Site": "Future Learn"
    }
}