{
    "metadataAttributes": {
        "Id": "3607",
        "Title": "Consumers and Ethical Considerations in the Fashion Industry",
        "URL": "https://www.futurelearn.com/courses/consumers-ethical-considerations-fashion-industry",
        "Short Intro": "Understand how ethics plays a role in consumer behaviour and how this affects decisions in the fashion industry.",
        "Category": "",
        "Sub-Category": "",
        "Course Type": "",
        "Language": "",
        "Skills": "",
        "Instructors": "",
        "Rating": "0.0",
        "Number of viewers": "",
        "Duration": "3 weeks",
        "Site": "Future Learn"
    }
}