{
    "metadataAttributes": {
        "Id": "3713",
        "Title": "Understanding Genetic Disorders: How DNA Influences Health",
        "URL": "https://www.futurelearn.com/courses/genes-and-health-how-dna-influences-disease",
        "Short Intro": "1,226\u00a0enrolled on this course",
        "Category": "",
        "Sub-Category": "",
        "Course Type": "",
        "Language": "",
        "Skills": "",
        "Instructors": "",
        "Rating": "0.0",
        "Number of viewers": "",
        "Duration": "4 weeks",
        "Site": "Future Learn"
    }
}