{
    "metadataAttributes": {
        "Id": "3787",
        "Title": "Introduction to Tools for Robotics",
        "URL": "https://www.futurelearn.com/courses/introduction-tools-for-robotics",
        "Short Intro": "Explore the different tools and software to design, test, and prototype custom robot parts and robust robot behaviour.",
        "Category": "",
        "Sub-Category": "",
        "Course Type": "",
        "Language": "",
        "Skills": "",
        "Instructors": "",
        "Rating": "0.0",
        "Number of viewers": "",
        "Duration": "3 weeks",
        "Site": "Future Learn"
    }
}