{
    "metadataAttributes": {
        "Id": "429",
        "Title": "Meta Front-End Developer Professional Certificate",
        "URL": "https://www.coursera.org/professional-certificates/meta-front-end-developer",
        "Short Intro": "Launch your career as a front-end developer. Build job-ready skills for an in-demand career and earn a credential from Meta. No degree or prior experience required to get started. ",
        "Category": "\u8ba1\u7b97\u673a\u79d1\u5b66",
        "Sub-Category": "\u79fb\u52a8\u548c\u7f51\u7edc\u5f00\u53d1",
        "Course Type": "Professional Certificate",
        "Language": "English",
        "Skills": "Cascading Style Sheets (CSS),HTML,UI/UX design,React,JavaScript,",
        "Instructors": "Taught by Meta Staff",
        "Rating": "4.7",
        "Number of viewers": "7,699 reviews",
        "Duration": "7 months at 6 hours a week",
        "Site": "Coursera"
    }
}