{
    "metadataAttributes": {
        "Id": "4540",
        "Title": "Introduction to Data Science for Business",
        "URL": "https://www.futurelearn.com/courses/introduction-to-data-science-for-business",
        "Short Intro": "Build a solid foundation in data science and learn how to analyse data and communicate insights in a business environment.",
        "Category": "",
        "Sub-Category": "",
        "Course Type": "",
        "Language": "",
        "Skills": "",
        "Instructors": "",
        "Rating": "0.0",
        "Number of viewers": "",
        "Duration": "4 weeks",
        "Site": "Future Learn"
    }
}