{
    "metadataAttributes": {
        "Id": "4570",
        "Title": "Discovering Science: Atmospheric Chemistry",
        "URL": "https://www.futurelearn.com/courses/discovering-science-atmospheric-chemistry",
        "Short Intro": "What can we learn about Earth, and other planets in and beyond our solar system, by studying their atmospheres?",
        "Category": "",
        "Sub-Category": "",
        "Course Type": "",
        "Language": "",
        "Skills": "",
        "Instructors": "",
        "Rating": "0.0",
        "Number of viewers": "",
        "Duration": "2 weeks",
        "Site": "Future Learn"
    }
}