{
    "metadataAttributes": {
        "Id": "4914",
        "Title": "Create Innovative Teams with Design Thinking",
        "URL": "https://www.futurelearn.com/courses/innovative-teams-with-design-thinking",
        "Short Intro": "Implement design thinking principles and team-based methods to support idea generation and create innovative teams.",
        "Category": "",
        "Sub-Category": "",
        "Course Type": "",
        "Language": "",
        "Skills": "",
        "Instructors": "",
        "Rating": "0.0",
        "Number of viewers": "",
        "Duration": "4 weeks",
        "Site": "Future Learn"
    }
}