{
    "metadataAttributes": {
        "Id": "50",
        "Title": "Python 3 Programming Specialization",
        "URL": "https://www.coursera.org/specializations/python-3-programming",
        "Short Intro": "Become a Fluent Python Programmer. Learn the fundamentals and become an independent programmer.",
        "Category": "Computer Science",
        "Sub-Category": "Software Development",
        "Course Type": "Specialization",
        "Language": "English",
        "Skills": "Json, Computer Programming, Python Programming, Sorting, ",
        "Instructors": "Paul Resnick ,Steve Oney ,Christopher Brooks ,",
        "Rating": "4.7",
        "Number of viewers": "15,871 ",
        "Duration": "Approximately 5 months to complete",
        "Site": "Coursera"
    }
}