{
    "metadataAttributes": {
        "Id": "5477",
        "Title": "Competitor Analysis: From Business Level Strategy to Organisational Structures",
        "URL": "https://www.futurelearn.com/courses/competitor-analysis-et",
        "Short Intro": "Discover how to implement successful corporate level strategy and robust organisational structures through competitive analysis.",
        "Category": "",
        "Sub-Category": "",
        "Course Type": "",
        "Language": "",
        "Skills": "",
        "Instructors": "",
        "Rating": "0.0",
        "Number of viewers": "",
        "Duration": "2 weeks",
        "Site": "Future Learn"
    }
}