{
    "metadataAttributes": {
        "Id": "5945",
        "Title": "Finding the Body\u2019s Balance: Understanding Homeostasis",
        "URL": "https://www.futurelearn.com/courses/finding-the-body-s-balance-understanding-homeostasis",
        "Short Intro": "Explore the role of homeostasis in maintaining life and investigate the factors that impact the body\u2019s ability to sustain balance.",
        "Category": "",
        "Sub-Category": "",
        "Course Type": "",
        "Language": "",
        "Skills": "",
        "Instructors": "",
        "Rating": "0.0",
        "Number of viewers": "",
        "Duration": "4 weeks",
        "Site": "Future Learn"
    }
}