{
    "metadataAttributes": {
        "Id": "5974",
        "Title": "Core Managers; Inclusive leadership in health and care",
        "URL": "https://www.futurelearn.com/courses/inclusive-leadership-in-health-and-care",
        "Short Intro": "Develop inclusive and compassionate leadership skills to ensure diversity and equality in the health and care industry.",
        "Category": "",
        "Sub-Category": "",
        "Course Type": "",
        "Language": "",
        "Skills": "",
        "Instructors": "",
        "Rating": "0.0",
        "Number of viewers": "",
        "Duration": "6 weeks",
        "Site": "Future Learn"
    }
}