{
    "metadataAttributes": {
        "Id": "6044",
        "Title": "Retinopathy of Prematurity: Practical Approaches to Prevent Blindness",
        "URL": "https://www.futurelearn.com/courses/retinopathy-of-prematurity-practical-approaches-to-prevent-blindness",
        "Short Intro": "Explore the strategies to prevent and treat retinopathy of prematurity (ROP) with this online course for healthcare professionals.",
        "Category": "",
        "Sub-Category": "",
        "Course Type": "",
        "Language": "",
        "Skills": "",
        "Instructors": "",
        "Rating": "0.0",
        "Number of viewers": "",
        "Duration": "4 weeks",
        "Site": "Future Learn"
    }
}