{
    "metadataAttributes": {
        "Id": "6093",
        "Title": "The Role of Vaccines in Preventing Infectious Diseases and Antimicrobial Resistance",
        "URL": "https://www.futurelearn.com/courses/the-role-of-vaccines-in-preventing-infectious-diseases-and-amr",
        "Short Intro": "Learn how vaccines work and can be used for infectious disease control with this online course for healthcare professionals.",
        "Category": "",
        "Sub-Category": "",
        "Course Type": "",
        "Language": "",
        "Skills": "",
        "Instructors": "",
        "Rating": "0.0",
        "Number of viewers": "",
        "Duration": "2 weeks",
        "Site": "Future Learn"
    }
}