{
    "metadataAttributes": {
        "Id": "6162",
        "Title": "Introduction to Health Technology Assessment",
        "URL": "https://www.futurelearn.com/courses/health-technology-assessment",
        "Short Intro": "Learn about health technology assessment (HTA) and quality of life (QoL), and how they\u2019re used to decide which treatments to fund",
        "Category": "",
        "Sub-Category": "",
        "Course Type": "",
        "Language": "",
        "Skills": "",
        "Instructors": "",
        "Rating": "0.0",
        "Number of viewers": "",
        "Duration": "3 weeks",
        "Site": "Future Learn"
    }
}