{
    "metadataAttributes": {
        "Id": "6338",
        "Title": "Cloud Computing for Beginners",
        "URL": "https://www.futurelearn.com/courses/cloud-computing-for-beginners",
        "Short Intro": "Explore the key characteristics of the Cloud and how you can improve computing processes with Cloud services.",
        "Category": "",
        "Sub-Category": "",
        "Course Type": "",
        "Language": "",
        "Skills": "",
        "Instructors": "",
        "Rating": "0.0",
        "Number of viewers": "",
        "Duration": "1 week",
        "Site": "Future Learn"
    }
}