{
    "metadataAttributes": {
        "Id": "6856",
        "Title": "Changing Urban Travel Behaviour for a Low-Carbon Transition",
        "URL": "https://www.futurelearn.com/courses/changing-urban-travel-behaviour-for-a-low-carbon-transition",
        "Short Intro": "Explore the determinants of transport behaviour and choices that promote low-carbon mobility.",
        "Category": "",
        "Sub-Category": "",
        "Course Type": "",
        "Language": "",
        "Skills": "",
        "Instructors": "",
        "Rating": "0.0",
        "Number of viewers": "",
        "Duration": "2 weeks",
        "Site": "Future Learn"
    }
}