{
    "metadataAttributes": {
        "Id": "6943",
        "Title": "Poultry Health",
        "URL": "https://www.futurelearn.com/courses/poultry-health",
        "Short Intro": "Get technically and scientifically accurate information on how to care for non-commercial poultry.",
        "Category": "",
        "Sub-Category": "",
        "Course Type": "",
        "Language": "",
        "Skills": "",
        "Instructors": "",
        "Rating": "0.0",
        "Number of viewers": "",
        "Duration": "6 weeks",
        "Site": "Future Learn"
    }
}