{
    "metadataAttributes": {
        "Id": "6994",
        "Title": "How Plants Grow: The Essentials",
        "URL": "https://www.futurelearn.com/courses/gardening-for-beginners-how-to-grow-plants-and-nurture-them-part-one-",
        "Short Intro": "464\u00a0enrolled on this course",
        "Category": "",
        "Sub-Category": "",
        "Course Type": "",
        "Language": "",
        "Skills": "",
        "Instructors": "",
        "Rating": "0.0",
        "Number of viewers": "",
        "Duration": "2 weeks",
        "Site": "Future Learn"
    }
}