{
    "metadataAttributes": {
        "Id": "7063",
        "Title": "Electric Mobility in the Age of Climate Change",
        "URL": "https://www.futurelearn.com/courses/real-estate-and-electric-mobility-in-the-age-of-climate-change",
        "Short Intro": "Explore the design and delivery of electric vehicle infrastructure to reduce carbon emissions in cities.",
        "Category": "",
        "Sub-Category": "",
        "Course Type": "",
        "Language": "",
        "Skills": "",
        "Instructors": "",
        "Rating": "0.0",
        "Number of viewers": "",
        "Duration": "2 weeks",
        "Site": "Future Learn"
    }
}