{
    "metadataAttributes": {
        "Id": "708",
        "Title": "Share Data Through the Art of Visualization",
        "URL": "https://www.coursera.org/learn/visualize-data",
        "Short Intro": "This is the sixth course in the Google Data Analytics Certificate. These courses will equip you with the skills needed to apply to introductory-level data analyst jobs. You\u2019ll learn how to visualize and present your data findings as you complete the data analysis process. This course will show you how data visualizations, such as visual dashboards, can help bring your data to life. You\u2019ll also explore Tableau, a data visualization platform that will help you create effective visualizations for your presentations. Current Google data analysts will continue to instruct and provide you with hands-on ways to accomplish common data analyst tasks with the best tools and resources.",
        "Category": "Data Science",
        "Sub-Category": "Data Analysis",
        "Course Type": "Course",
        "Language": "English",
        "Skills": "Data Analysis,Tableau Software,Data Visualization (DataViz),Presentation,",
        "Instructors": "Google Career Certificates",
        "Rating": "4.6",
        "Number of viewers": "6,342 ",
        "Duration": "Approx. 24 hours to complete",
        "Site": "Coursera"
    }
}