{
    "metadataAttributes": {
        "Id": "7206",
        "Title": "Working Supportively With Refugees: Principles, Skills and Perspectives",
        "URL": "https://www.futurelearn.com/courses/working-supportively-with-refugees",
        "Short Intro": "Learn how the principles of psychological well-being, communication and interpretation can benefit your work with refugees",
        "Category": "",
        "Sub-Category": "",
        "Course Type": "",
        "Language": "",
        "Skills": "",
        "Instructors": "",
        "Rating": "0.0",
        "Number of viewers": "",
        "Duration": "3 weeks",
        "Site": "Future Learn"
    }
}