{
    "metadataAttributes": {
        "Id": "7445",
        "Title": "Blue Tomorrow: Understanding the Blue Economy",
        "URL": "https://www.futurelearn.com/courses/blue-tomorrow-understanding-the-blue-economy",
        "Short Intro": "Find your path to an impactful and rewarding career in the biggest opportunity on the planet, the blue economy.",
        "Category": "",
        "Sub-Category": "",
        "Course Type": "",
        "Language": "",
        "Skills": "",
        "Instructors": "",
        "Rating": "0.0",
        "Number of viewers": "",
        "Duration": "4 weeks",
        "Site": "Future Learn"
    }
}