{
    "metadataAttributes": {
        "Id": "7670",
        "Title": "Preparing to Learn Online at University",
        "URL": "https://www.futurelearn.com/courses/preparing-to-learn-online-at-university",
        "Short Intro": "Need advice on how to study online? Discover study techniques and skills for learning online as part of your university studies.",
        "Category": "",
        "Sub-Category": "",
        "Course Type": "",
        "Language": "",
        "Skills": "",
        "Instructors": "",
        "Rating": "0.0",
        "Number of viewers": "",
        "Duration": "3 weeks",
        "Site": "Future Learn"
    }
}