{
    "metadataAttributes": {
        "Id": "7789",
        "Title": "Guided Case Study of an English Language Learner",
        "URL": "https://www.futurelearn.com/courses/guided-case-study-of-an-english-language-learner",
        "Short Intro": "Build your knowledge of language learners and learn key language teaching strategies through a guided case study of a student.",
        "Category": "",
        "Sub-Category": "",
        "Course Type": "",
        "Language": "",
        "Skills": "",
        "Instructors": "",
        "Rating": "0.0",
        "Number of viewers": "",
        "Duration": "6 weeks",
        "Site": "Future Learn"
    }
}