{
    "metadataAttributes": {
        "Id": "8006",
        "Title": "Big Data Engineer",
        "URL": "https://www.simplilearn.com/search?item_type=course%2Cbundle%2Ccohort_master%2Cuniversity_master&tag=Big%20Data%20Engineer",
        "Short Intro": "This Big Data Engineer course features masterclasses and Ask me anything sessions by IBM experts. Learn job critical skills with our master's program, like Big Data & Hadoop frameworks, and leverage the functionality of AWS services. The Big Data Engineer course helps you learn to use the database management tool and MongoDB via interactive sessions & industry projects.",
        "Category": "",
        "Sub-Category": "",
        "Course Type": "",
        "Language": "",
        "Skills": "",
        "Instructors": "",
        "Rating": "0.0",
        "Number of viewers": "",
        "Duration": "",
        "Site": "Simplilearn"
    }
}