{
    "metadataAttributes": {
        "Id": "8059",
        "Title": "Salesforce Platform App Builder Certification Training",
        "URL": "https://www.simplilearn.com/salesforce/salesforce-developer-training?tag=",
        "Short Intro": "Kickstart your career with this the Salesforce Platform App Builder Certification program. Salesforce skills are in high demand, and you can learn the core concepts of online application development using Salesforce App Builder and Force.com Platform Fundamentals.",
        "Category": "",
        "Sub-Category": "",
        "Course Type": "",
        "Language": "",
        "Skills": "",
        "Instructors": "",
        "Rating": "0.0",
        "Number of viewers": "",
        "Duration": "",
        "Site": "Simplilearn"
    }
}