{
    "metadataAttributes": {
        "Id": "907",
        "Title": "Diversity and Inclusion for HR Professionals",
        "URL": "https://www.coursera.org/learn/diversity-and-inclusion-for-hr-professionals",
        "Short Intro": "Welcome to Diversity & Inclusion for HR Professionals. In this course we will review the changing landscape of the workplace and discuss the current change drivers that make Diversity and Inclusion an important focus for your organization. We will explore strategies for creating an inclusive climate and a sense of belonging, and how bias and microaggressions can be mitigated. Finally, we will explore the business case for Diversity and Inclusion strategies, and you\u2019ll have the opportunity to develop a DEIB tailored to your organization and situation.",
        "Category": "Business",
        "Sub-Category": "Leadership and Management",
        "Course Type": "Course",
        "Language": "English",
        "Skills": "inclusion,diversity,belonging,Human Resources (HR),Leadership,",
        "Instructors": "Diane Spiegel",
        "Rating": "4.7",
        "Number of viewers": "138 ",
        "Duration": "Approx. 16 hours to complete",
        "Site": "Coursera"
    }
}