{
    "metadataAttributes": {
        "Id": "923",
        "Title": "Business Model Innovation",
        "URL": "https://www.coursera.org/learn/business-model",
        "Short Intro": "Innovation goes beyond technology, products and processes. The new competitive landscape requires another, more holistic and strategic perspective, based on the concept of business models.",
        "Category": "Business",
        "Sub-Category": "Business Strategy",
        "Course Type": "Course",
        "Language": "English",
        "Skills": "Strategic Management,Business Model,Business Modeling,Business Strategy,",
        "Instructors": "Laurence Lehmann-Ortega",
        "Rating": "4.7",
        "Number of viewers": "485 ",
        "Duration": "Approx. 14 hours to complete",
        "Site": "Coursera"
    }
}